causalgraphicalmodels/__init__.py
causalgraphicalmodels/cgm.py
causalgraphicalmodels/csm.py
causalgraphicalmodels/examples.py
causalgraphicalmodels-0.0.4.dist-info/DESCRIPTION.rst
causalgraphicalmodels-0.0.4.dist-info/METADATA
causalgraphicalmodels-0.0.4.dist-info/RECORD
causalgraphicalmodels-0.0.4.dist-info/WHEEL
causalgraphicalmodels-0.0.4.dist-info/metadata.json
causalgraphicalmodels-0.0.4.dist-info/top_level.txt
tests/__init__.py
tests/test_cgm.py
tests/test_sgm.py
