Metadata-Version: 1.1
Name: causalgraphicalmodels
Version: 0.0.4
Summary: Causality Graphical Models in Python
Home-page: https://github.com/ijmbarr/causalgraphicalmodels
Author: Iain Barr
Author-email: iain@degeneratestate.org
License: MIT
Keywords: causal inference causal graphical models causality
Platform: UNKNOWN
Classifier: Development Status :: 2 - Pre-Alpha
Classifier: Intended Audience :: Science/Research
Classifier: Topic :: Scientific/Engineering
Classifier: License :: OSI Approved :: MIT License
Classifier: Programming Language :: Python :: 3.5
